numdata/__init__.py
numdata/calculate.py
numdata-2.0.0.dist-info/METADATA
numdata-2.0.0.dist-info/RECORD
numdata-2.0.0.dist-info/WHEEL
numdata-2.0.0.dist-info/top_level.txt
