Metadata-Version: 2.1
Name: numdata
Version: 2.0.0
Summary: A simple package calculating values for a simgle number and created in my Udemy course
Home-page: UNKNOWN
Author: Vinay Phadnis
Author-email: abc@xyz.com
License: UNKNOWN
Keywords: package numbers calculations
Platform: UNKNOWN
Classifier: Programming Language :: Python :: 2
Classifier: Operating System :: OS Independent
